CHANGELOG.rst
LICENSE
MANIFEST.in
README.rst
setup.py
django_ember.egg-info/PKG-INFO
django_ember.egg-info/SOURCES.txt
django_ember.egg-info/dependency_links.txt
django_ember.egg-info/requires.txt
django_ember.egg-info/top_level.txt
ember/__init__.py
ember/models.py
ember/settings.py
ember/test_urls.py
ember/tests.py
ember/wsgi.py
ember/static/js/libs/ember-data.js
ember/static/js/libs/ember-data.min.js
ember/static/js/libs/ember.js
ember/static/js/libs/ember.min.js
ember/static/js/libs/handlebars.js
ember/static/js/libs/handlebars.min.js
ember/static/js/libs/tastypie_adapter.js
ember/static/js/libs/tastypie_adapter.min.js
ember/static/js/specs/django-ember.specs.js
ember/templates/ember/django_ember_js_tag.html
ember/templates/ember/jasmine-runner.html
ember/templates/ember/test/jasmine-runner.html
ember/templatetags/__init__.py
ember/templatetags/ember.py
requirements/develop.pip
requirements/install.pip
requirements/test.pip